notapy/__init__.py
notapy/converter.py
notapy-0.2.0.dist-info/LICENSE
notapy-0.2.0.dist-info/METADATA
notapy-0.2.0.dist-info/WHEEL
notapy-0.2.0.dist-info/top_level.txt
notapy-0.2.0.dist-info/RECORD
